setup.py
ImportParseData/__init__.py
ImportParseData/import-parse-to-apiOmat
import_parse_to_apiOmat.egg-info/PKG-INFO
import_parse_to_apiOmat.egg-info/SOURCES.txt
import_parse_to_apiOmat.egg-info/dependency_links.txt
import_parse_to_apiOmat.egg-info/top_level.txt