Metadata-Version: 1.0
Name: import-parse-to-apiOmat
Version: 1.0
Summary: Import your data from Parse to apiOmat
Home-page: https://github.com/apiOmat/apiOmat-import-parse
Author: UNKNOWN
Author-email: UNKNOWN
License: UNKNOWN
Platform: UNKNOWN
